<?xml version="1.0" encoding="utf-8"?><!--
/**
 * @copyright	Copyright © 2015 - All rights reserved.
 * @license		GNU General Public License v2.0
 * @generator	hhp://xdsoft/joomla-module-generator/
 */
-->
<extension type="module" method="upgrade" client="">
	<name>MOD_CREATE_A_NEW_AUCTION</name>
	<creationDate>Nov 2015</creationDate>
	<author>Bipin Thakur</author>
	<authorEmail>bipin.singh@emptask.com</authorEmail>
	<authorUrl>http://appmeadows.com</authorUrl>
	<copyright>Copyright © 2015 - All rights reserved.</copyright>
	<license>GNU General Public License v2.0</license>
	<version>0.0.1</version>
	<description>MOD__P_SHOWS_CREATE_NEW_AUCTION_</description>
	<files>
		<filename module="mod_create_a_new_auction">mod_create_a_new_auction.php</filename>
		<filename>mod_create_a_new_auction.xml</filename>
		<filename>index.html</filename>
		<folder>language</folder>
		<folder>tmpl</folder>
		<folder>assets</folder>
	</files>
	<config>
		<fields name="params">
			<fieldset
				name="advanced">
				<field
					name="layout"
					type="modulelayout"
					label="JFIELD_ALT_LAYOUT_LABEL"
					description="JFIELD_ALT_MODULE_LAYOUT_DESC" />

				<field
					name="moduleclass_sfx"
					type="textarea" rows="3"
					label="COM_MODULES_FIELD_MODULECLASS_SFX_LABEL"
					description="COM_MODULES_FIELD_MODULECLASS_SFX_DESC" />

				<field
					name="cache"
					type="list"
					default="1"
					label="COM_MODULES_FIELD_CACHING_LABEL"
					description="COM_MODULES_FIELD_CACHING_DESC">
					<option
						value="1">JGLOBAL_USE_GLOBAL</option>
					<option
						value="0">COM_MODULES_FIELD_VALUE_NOCACHING</option>
				</field>

				<field
					name="cache_time"
					type="text"
					default="900"
					label="COM_MODULES_FIELD_CACHE_TIME_LABEL"
					description="COM_MODULES_FIELD_CACHE_TIME_DESC" />
				<field
					name="cachemode"
					type="hidden"
					default="static">
					<option
						value="static"></option>
				</field>
			</fieldset>
</fields>
<!--
########################################################################################
The following are a list of all the different types of fields you can add to this file
They are here for copy pasting - neat eh?
########################################################################################

http://docs.joomla.org/Calendar_parameter_type
<field name="mycalendar" type="calendar" default="5-10-2008" label="Select a date" description="" format="%d-%m-%Y" />

http://docs.joomla.org/Category_parameter_type
<field name="mycategory" type="category" label="Select a category" description="" section="3" />

http://docs.joomla.org/Editors_parameter_type
<field name="myeditor" type="editors" default="none" label="Select an editor" />

http://docs.joomla.org/Filelist_parameter_type
<field name="myfile" type="filelist" default="" label="Select a file" description="" directory="administrator" filter="" exclude="" stripext="" />

http://docs.joomla.org/Folderlist_parameter_type
<field name="myfolder" type="folderlist" default="" label="Select a folder" directory="administrator" filter="" exclude="" stripext="" />

http://docs.joomla.org/Helpsites_parameter_type
<field name="myhelpsite" type="helpsites" default="" label="Select a help site" description="" />

http://docs.joomla.org/Hidden_parameter_type
<field name="mysecretvariable" type="hidden" default="" />

http://docs.joomla.org/Imagelist_parameter_type
<field name="myimage" type="imagelist" default="" label="Select an image" description="" directory="" exclude="" stripext="" />

http://docs.joomla.org/Languages_parameter_type
<field name="mylanguage" type="languages" client="site" default="en-GB" label="Select a language" description="" />

http://docs.joomla.org/List_parameter_type
<field name="mylistvalue" type="list" default="" label="Select an option" description="">
  <option value="0">Option 1</option>
  <option value="1">Option 2</option>
</field>

http://docs.joomla.org/Menu_parameter_type
<field name="mymenu" type="menu" default="mainmenu" label="Select a menu" description="Select a menu" />

http://docs.joomla.org/Menuitem_parameter_type
<field name="mymenuitem" type="menuitem" default="45" label="Select a menu item" description="Select a menu item" />

http://docs.joomla.org/Password_parameter_type
<field name="mypassword" type="password" default="secret" label="Enter a password" description="" size="5" />

http://docs.joomla.org/Radio_parameter_type
<field name="myradiovalue" type="radio" default="0" label="Select an option" description="">
  <option value="0">1</option>
  <option value="1">2</option>
</field>

http://docs.joomla.org/Spacer_parameter_type
<field type="spacer" default="&lt;b&gt;Advanced parameters&lt;/b&gt;" />

http://docs.joomla.org/Sql_parameter_type
<field name="myfield" type="sql" default="10" label="Select an article" query="SELECT id, title FROM #__content" key_field="id" value_field="title" />

http://docs.joomla.org/Text_parameter_type
<field name="mytextvalue" type="text" default="Some text" label="Enter some text" description="" size="10" />

http://docs.joomla.org/Textarea_parameter_type
<field name="mytextarea" type="textarea" default="default" label="Enter some text" description="" rows="10" cols="5" />

http://docs.joomla.org/Timezones_parameter_type
<field name="mytimezone" type="timezones" default="-10" label="Select a timezone" description="" />

http://docs.joomla.org/Usergroup_parameter_type
<field name="myusergroups" type="usergroup" default="" label="Select a user group" description="" />
-->
	</config> 
	<languages folder="language">
		<language tag="en-GB">en-GB/en-GB.mod_create_a_new_auction.sys.ini</language>
		<language tag="en-GB">en-GB/en-GB.mod_create_a_new_auction.ini</language>
		<language tag="ru-RU">ru-RU/ru-RU.mod_create_a_new_auction.sys.ini</language>
		<language tag="ru-RU">ru-RU/ru-RU.mod_create_a_new_auction.ini</language>
	</languages>
</extension>